gradle.properties
hexdoc_mediatransport/__gradle_version__.py
hexdoc_mediatransport/__init__.py
hexdoc_mediatransport/__version__.py
hexdoc_mediatransport/_hooks.py
hexdoc_mediatransport/api.py
hexdoc_mediatransport/builtin_extensions.py
hexdoc_mediatransport/diagrams.py
hexdoc_mediatransport/lang.py
hexdoc_mediatransport/plugins.py
hexdoc_mediatransport/prettylog.py
hexdoc_mediatransport/py.typed
hexdoc_mediatransport/_export/.gitignore
hexdoc_mediatransport/_export/__init__.py
hexdoc_mediatransport/_export/generated/__init__.py
hexdoc_mediatransport/_export/generated/mediatransport.hexdoc.json
hexdoc_mediatransport/_export/generated/mediatransport.patterns.hexdoc.json
hexdoc_mediatransport/_export/generated/assets/hexcasting/patchouli_books/thehexbook/en_us/categories/mediatransport_admin_virtual.json5
hexdoc_mediatransport/_export/generated/assets/hexcasting/patchouli_books/thehexbook/en_us/categories/interop/figura.json5
hexdoc_mediatransport/_export/generated/assets/hexcasting/patchouli_books/thehexbook/en_us/entries/interop/figura/about.json5
hexdoc_mediatransport/_export/generated/assets/hexcasting/patchouli_books/thehexbook/en_us/entries/interop/figura/channels.json5
hexdoc_mediatransport/_export/generated/assets/hexcasting/patchouli_books/thehexbook/en_us/entries/interop/figura/index.json5
hexdoc_mediatransport/_export/generated/assets/hexcasting/patchouli_books/thehexbook/en_us/entries/interop/figura/mishaps.json5
hexdoc_mediatransport/_export/generated/assets/hexcasting/patchouli_books/thehexbook/en_us/entries/mediatransport_virtual/api.json5
hexdoc_mediatransport/_export/generated/assets/hexcasting/patchouli_books/thehexbook/en_us/entries/mediatransport_virtual/config.json5
hexdoc_mediatransport/_export/generated/assets/hexcasting/patchouli_books/thehexbook/en_us/entries/mediatransport_virtual/fsb.json5
hexdoc_mediatransport/_export/generated/assets/hexcasting/patchouli_books/thehexbook/en_us/entries/mediatransport_virtual/protocol.json5
hexdoc_mediatransport-1.1.1.1.20.1.2.0.dist-info/METADATA
hexdoc_mediatransport-1.1.1.1.20.1.2.0.dist-info/WHEEL
hexdoc_mediatransport-1.1.1.1.20.1.2.0.dist-info/entry_points.txt
hexdoc_mediatransport-1.1.1.1.20.1.2.0.dist-info/licenses/LICENSE
hexdoc_mediatransport-1.1.1.1.20.1.2.0.dist-info/RECORD
