Metadata-Version: 2.4
Name: hexdoc-mediatransport
Version: 1.1.1.1.20.1.2.0
Summary: hex casting - fsb integration (the dev version of 1.20.1 figura)
Project-URL: Homepage, https://penguinencounter.github.io/mediatransport
Project-URL: Source, https://github.com/penguinencounter/mediatransport
Author: penguinencounter
License-File: LICENSE
Keywords: hexdoc
Requires-Python: >=3.11
Requires-Dist: hexdoc-hexcasting~=0.11.2.1.0
Requires-Dist: hexdoc>=1!0.1.0a31
Requires-Dist: pluggy~=1.6.0
Provides-Extra: dev
Requires-Dist: ruff~=0.11.13; extra == 'dev'
